[
    {
        "spotId": "zCwOtcmTUaZ05EoPbRaM",
        "startTime": "6:00 PM",
        "date": "04/07/2024",
        "spotName": "Raleigh Convention Center",
        "endTime": "7:00 PM",
        "spotRegion": "Fayetteville Street",
        "id": "2AA8QsUKylqi25M0NyLt"
    },
    {
        "spotId": "KUmCTbDqocu9nshddx44",
        "startTime": "7:00 PM",
        "date": "04/06/2024",
        "spotName": "The Raleigh Depot",
        "endTime": "8:00 PM",
        "spotRegion": "Warehouse District",
        "id": "2dsmiGt0AfSEQH94ILGa"
    },
    {
        "spotId": "zCwOtcmTUaZ05EoPbRaM",
        "startTime": "3:00 PM",
        "date": "04/07/2024",
        "spotName": "Raleigh Convention Center",
        "endTime": "4:00 PM",
        "spotRegion": "Fayetteville Street",
        "id": "5E1LnKHTTLIL7GkqFqWi"
    },
    {
        "spotId": "KUmCTbDqocu9nshddx44",
        "startTime": "6:00 PM",
        "date": "04/07/2024",
        "spotName": "The Raleigh Depot",
        "endTime": "7:00 PM",
        "spotRegion": "Warehouse District",
        "id": "75FLWVVeMO8i9ZDk2ff7"
    },
    {
        "spotId": "RKhtn3Gr3WYmf4cyaaTT",
        "startTime": "6:00 PM",
        "date": "04/07/2024",
        "spotName": "Courthouse Plaza",
        "endTime": "7:00 PM",
        "spotRegion": "Fayetteville Street",
        "id": "7qD4THpOwBUHadJZumfj"
    },
    {
        "spotId": "RQcWLwgIb9fooEdxQap4",
        "startTime": "4:00 PM",
        "date": "04/07/2024",
        "spotName": "Exchange Plaza",
        "endTime": "5:00 PM",
        "spotRegion": "Fayetteville Street",
        "id": "834zJYnPrIrxu1QSfxZ5"
    },
    {
        "spotId": "XMo7AYD1SHKkPSdnWRXe",
        "startTime": "7:00 PM",
        "date": "04/07/2024",
        "spotName": "The Acorn",
        "endTime": "8:00 PM",
        "spotRegion": "Fayetteville Street",
        "id": "AFUSKLTzSfDPZ09S1nKg"
    },
    {
        "spotId": "RQcWLwgIb9fooEdxQap4",
        "startTime": "6:00 PM",
        "date": "04/06/2024",
        "spotName": "Exchange Plaza",
        "endTime": "7:00 PM",
        "spotRegion": "Fayetteville Street",
        "id": "E3Tixz8wWkrIuXEs09AV"
    },
    {
        "spotId": "01BS8Q3ZFlLWq3FtB6UU",
        "startTime": "5:00 PM",
        "date": "04/06/2024",
        "spotName": "Weaver Street Market",
        "endTime": "6:00 PM",
        "spotRegion": "Warehouse District",
        "id": "IO01YdiyAhpmSzwyOlD0"
    },
    {
        "spotId": "RKhtn3Gr3WYmf4cyaaTT",
        "startTime": "5:00 PM",
        "date": "04/06/2024",
        "spotName": "Courthouse Plaza",
        "endTime": "6:00 PM",
        "spotRegion": "Fayetteville Street",
        "id": "IhVBRrAOZM2vvi4xKXro"
    },
    {
        "spotId": "2tnuhutovCU5h3zRFQbJ",
        "startTime": "7:00 PM",
        "date": "04/06/2024",
        "spotName": "Smoky Hollows",
        "endTime": "8:00 PM",
        "spotRegion": "Glenwood Avenue",
        "id": "K3PcpKvfPiFJc6DPTYNV"
    },
    {
        "spotId": "01BS8Q3ZFlLWq3FtB6UU",
        "startTime": "7:00 PM",
        "date": "04/07/2024",
        "spotName": "Weaver Street Market",
        "endTime": "8:00 PM",
        "spotRegion": "Warehouse District",
        "id": "Leurd0ehlJCb5Yr2IMHh"
    },
    {
        "spotId": "FGKLt0f9HR0f3pPGZZYN",
        "startTime": "3:00 PM",
        "date": "04/07/2024",
        "spotName": "Lichtin Plaza",
        "endTime": "4:00 PM",
        "spotRegion": "Fayetteville Street",
        "id": "PA1FFF6UmOWPkWUAcOVu"
    },
    {
        "spotId": "RQcWLwgIb9fooEdxQap4",
        "startTime": "8:00 PM",
        "date": "04/06/2024",
        "spotName": "Exchange Plaza",
        "endTime": "9:00 PM",
        "spotRegion": "Fayetteville Street",
        "id": "PQ5siQLjfgmUFUrFbo1N"
    },
    {
        "spotId": "FGKLt0f9HR0f3pPGZZYN",
        "startTime": "5:00 PM",
        "date": "04/07/2024",
        "spotName": "Lichtin Plaza",
        "endTime": "6:00 PM",
        "spotRegion": "Fayetteville Street",
        "id": "QIwwPtP5iX9s8x8o0Nhj"
    },
    {
        "spotId": "zCwOtcmTUaZ05EoPbRaM",
        "startTime": "4:00 PM",
        "date": "04/06/2024",
        "spotName": "Raleigh Convention Center",
        "endTime": "5:00 PM",
        "spotRegion": "Fayetteville Street",
        "id": "RqV8mRF2oApmxOQRGvfx"
    },
    {
        "spotId": "KUmCTbDqocu9nshddx44",
        "startTime": "4:00 PM",
        "date": "04/07/2024",
        "spotName": "The Raleigh Depot",
        "endTime": "5:00 PM",
        "spotRegion": "Warehouse District",
        "id": "WMveIN01CTf6r2hm0evR"
    },
    {
        "spotId": "RKhtn3Gr3WYmf4cyaaTT",
        "startTime": "3:00 PM",
        "date": "04/06/2024",
        "spotName": "Courthouse Plaza",
        "endTime": "4:00 PM",
        "spotRegion": "Fayetteville Street",
        "id": "YEipcShvTh2t9Fp27Ovd"
    },
    {
        "spotId": "XMo7AYD1SHKkPSdnWRXe",
        "startTime": "1:00 PM",
        "date": "04/07/2024",
        "spotName": "The Acorn",
        "endTime": "2:00 PM",
        "spotRegion": "Fayetteville Street",
        "id": "YqXp3o3wakiz2Ja6jRav"
    },
    {
        "spotId": "01BS8Q3ZFlLWq3FtB6UU",
        "startTime": "5:00 PM",
        "date": "04/07/2024",
        "spotName": "Weaver Street Market",
        "endTime": "6:00 PM",
        "spotRegion": "Warehouse District",
        "id": "caWdHS6HK4g2EOurJL2d"
    },
    {
        "spotId": "RQcWLwgIb9fooEdxQap4",
        "startTime": "6:00 PM",
        "date": "04/07/2024",
        "spotName": "Exchange Plaza",
        "endTime": "7:00 PM",
        "spotRegion": "Fayetteville Street",
        "id": "dbPeK9hfa4hKiwevA27l"
    },
    {
        "spotId": "2tnuhutovCU5h3zRFQbJ",
        "startTime": "5:00 PM",
        "date": "04/06/2024",
        "spotName": "Smoky Hollows",
        "endTime": "6:00 PM",
        "spotRegion": "Glenwood Avenue",
        "id": "fOOKWm8whcYjuRjAAmzE"
    },
    {
        "spotId": "FGKLt0f9HR0f3pPGZZYN",
        "startTime": "6:00 PM",
        "date": "04/06/2024",
        "spotName": "Lichtin Plaza",
        "endTime": "7:00 PM",
        "spotRegion": "Fayetteville Street",
        "id": "fQcvCF2rpCqlLcPUq2GT"
    },
    {
        "spotId": "XMo7AYD1SHKkPSdnWRXe",
        "startTime": "9:00 PM",
        "date": "04/06/2024",
        "spotName": "The Acorn",
        "endTime": "10:00 PM",
        "spotRegion": "Fayetteville Street",
        "id": "lfujw6PzZA0LNRcDw7Td"
    },
    {
        "spotId": "KUmCTbDqocu9nshddx44",
        "startTime": "5:00 PM",
        "date": "04/06/2024",
        "spotName": "The Raleigh Depot",
        "endTime": "6:00 PM",
        "spotRegion": "Warehouse District",
        "id": "mRMf1OVjyH8Jw7qvcPR9"
    },
    {
        "spotId": "FGKLt0f9HR0f3pPGZZYN",
        "startTime": "8:00 PM",
        "date": "04/06/2024",
        "spotName": "Lichtin Plaza",
        "endTime": "9:00 PM",
        "spotRegion": "Fayetteville Street",
        "id": "r0WNas1QAfDPJicaD6p9"
    },
    {
        "spotId": "zCwOtcmTUaZ05EoPbRaM",
        "startTime": "8:00 PM",
        "date": "04/06/2024",
        "spotName": "Raleigh Convention Center",
        "endTime": "9:00 PM",
        "spotRegion": "Fayetteville Street",
        "id": "smg7HHKP2zA4Zg4OGJAt"
    },
    {
        "spotId": "XMo7AYD1SHKkPSdnWRXe",
        "startTime": "5:00 PM",
        "date": "04/06/2024",
        "spotName": "The Acorn",
        "endTime": "6:00 PM",
        "spotRegion": "Fayetteville Street",
        "id": "u1RJRZDGDj9cXth0mnIH"
    },
    {
        "spotId": "RKhtn3Gr3WYmf4cyaaTT",
        "startTime": "3:00 PM",
        "date": "04/07/2024",
        "spotName": "Courthouse Plaza",
        "endTime": "4:00 PM",
        "spotRegion": "Fayetteville Street",
        "id": "uGgefKXe7fRe1IHNwB6v"
    },
    {
        "spotId": "01BS8Q3ZFlLWq3FtB6UU",
        "startTime": "7:00 PM",
        "date": "04/06/2024",
        "spotName": "Weaver Street Market",
        "endTime": "8:00 PM",
        "spotRegion": "Warehouse District",
        "id": "zh7oMR17bemh7QWwxlyT"
    }
]